polaris/__init__.py
polaris/Coordinates/__init__.py
polaris/Coordinates/_plot_circle.py
polaris/Coordinates/_transformations.py
polaris/Keplerian/__init__.py
polaris/Keplerian/_conicElements.py
polaris/Keplerian/_miscExpressions.py
polaris/Keplerian/_statevec2elements.py
polaris/Propagator/__init__.py
polaris/Propagator/_jitcode_propagator.py
polaris/Propagator/_propagator_bcr4bp.py
polaris/Propagator/_propagator_ccr4bp.py
polaris/Propagator/_propagator_cr3bp.py
polaris/Propagator/_propagator_cr3bp_thrust.py
polaris/Propagator/_propagator_pcr3bp.py
polaris/Propagator/_propagator_twobody.py
polaris/Propagator/_rhs_functions.py
polaris/Propagator/_ssdc.py
polaris/R3BP/__init__.py
polaris/R3BP/_approxHalo3rdOrder.py
polaris/R3BP/_approxTriangularLibPoints.py
polaris/R3BP/_circularize_cost.py
polaris/R3BP/_define_r3bp_param.py
polaris/R3BP/_jacobiConstant.py
polaris/R3BP/_jacobiContour.py
polaris/R3BP/_lagrangePoints.py
polaris/R3BP/_manifold.py
polaris/R3BP/_ssdc_periodic_xzplane.py
polaris/R3BP/_stabilityIndex.py
astro_polaris-0.1.3.dist-info/LICENSE
astro_polaris-0.1.3.dist-info/METADATA
astro_polaris-0.1.3.dist-info/WHEEL
astro_polaris-0.1.3.dist-info/top_level.txt
astro_polaris-0.1.3.dist-info/RECORD
